MANIFEST.in
README.rst
igloo.py
setup.py
igloo.egg-info/PKG-INFO
igloo.egg-info/SOURCES.txt
igloo.egg-info/dependency_links.txt
igloo.egg-info/entry_points.txt
igloo.egg-info/requires.txt
igloo.egg-info/top_level.txt