Metadata-Version: 1.1
Name: igloo
Version: 0.1.1
Summary: A command line SCP client
Home-page: http://github.com/mtth/igloo/
Author: Matthieu Monsch
Author-email: monsch@mit.edu
License: MIT
Platform: UNKNOWN
Classifier: Development Status :: 4 - Beta
Classifier: Intended Audience :: Developers
Classifier: License :: OSI Approved :: MIT License
Classifier: Programming Language :: Python
